<?xml version="1.0" encoding="utf-8" ?>
<dwsync>
<file name="alter_buttons.html" server="192.168.0.102" local="130462083232652217" remote="130462192800000000" Dst="1" />
<file name="bootstrap.html" server="192.168.0.102" local="130462083232662214" remote="130462192800000000" Dst="1" />
<file name="button_text.html" server="192.168.0.102" local="130462083232662214" remote="130462192800000000" Dst="1" />
<file name="collection.html" server="192.168.0.102" local="130462083232672225" remote="130462192800000000" Dst="1" />
<file name="defaults.html" server="192.168.0.102" local="130462083232672225" remote="130462192800000000" Dst="1" />
<file name="index.html" server="192.168.0.102" local="130462083233252252" remote="130462192800000000" Dst="1" />
<file name="multiple_tables.html" server="192.168.0.102" local="130462083233262263" remote="130462192800000000" Dst="1" />
<file name="multi_instance.html" server="192.168.0.102" local="130462083233252252" remote="130462192800000000" Dst="1" />
<file name="new_init.html" server="192.168.0.102" local="130462083233262263" remote="130462192800000000" Dst="1" />
<file name="pdf_message.html" server="192.168.0.102" local="130462083233272264" remote="130462192800000000" Dst="1" />
<file name="plug-in.html" server="192.168.0.102" local="130462083233272264" remote="130462192800000000" Dst="1" />
<file name="select_column.html" server="192.168.0.102" local="130462083233282262" remote="130462192800000000" Dst="1" />
<file name="select_multi.html" server="192.168.0.102" local="130462083233282262" remote="130462192800000000" Dst="1" />
<file name="select_os.html" server="192.168.0.102" local="130462083233292259" remote="130462192800000000" Dst="1" />
<file name="select_single.html" server="192.168.0.102" local="130462083233292259" remote="130462192800000000" Dst="1" />
<file name="simple.html" server="192.168.0.102" local="130462083233302256" remote="130462192800000000" Dst="1" />
<file name="swf_path.html" server="192.168.0.102" local="130462083233302256" remote="130462192800000000" Dst="1" />
</dwsync>